urdf_usd_converter/__init__.py
urdf_usd_converter/__main__.py
urdf_usd_converter/_version.py
urdf_usd_converter/_impl/_flatten.py
urdf_usd_converter/_impl/cli.py
urdf_usd_converter/_impl/conversion_collada.py
urdf_usd_converter/_impl/convert.py
urdf_usd_converter/_impl/data.py
urdf_usd_converter/_impl/geometry.py
urdf_usd_converter/_impl/link.py
urdf_usd_converter/_impl/link_hierarchy.py
urdf_usd_converter/_impl/material.py
urdf_usd_converter/_impl/material_cache.py
urdf_usd_converter/_impl/material_data.py
urdf_usd_converter/_impl/mesh.py
urdf_usd_converter/_impl/mesh_cache.py
urdf_usd_converter/_impl/numpy.py
urdf_usd_converter/_impl/planar_joint.py
urdf_usd_converter/_impl/ros_package.py
urdf_usd_converter/_impl/scene.py
urdf_usd_converter/_impl/utils.py
urdf_usd_converter/_impl/urdf_parser/elements.py
urdf_usd_converter/_impl/urdf_parser/line_number_parser.py
urdf_usd_converter/_impl/urdf_parser/parser.py
urdf_usd_converter/_impl/urdf_parser/reserved_element_attribute_names.py
urdf_usd_converter/_impl/urdf_parser/undefined_data.py
urdf_usd_converter-0.1.0a2.dist-info/METADATA
urdf_usd_converter-0.1.0a2.dist-info/WHEEL
urdf_usd_converter-0.1.0a2.dist-info/entry_points.txt
urdf_usd_converter-0.1.0a2.dist-info/licenses/LICENSE.md
urdf_usd_converter-0.1.0a2.dist-info/RECORD
