Metadata-Version: 2.4
Name: urdf-usd-converter
Version: 0.1.0a2
Summary: A URDF to OpenUSD Data Converter
Project-URL: Documentation, https://github.com/newton-physics/urdf-usd-converter/#readme
Project-URL: Repository, https://github.com/newton-physics/urdf-usd-converter
Project-URL: Changelog, https://github.com/newton-physics/urdf-usd-converter/blob/main/CHANGELOG.md
Author: Newton Developers
License: Apache-2.0
License-File: LICENSE.md
Requires-Python: <3.13,>=3.10
Requires-Dist: numpy-stl>=3.2
Requires-Dist: pycollada>=0.9.2
Requires-Dist: tinyobjloader>=2.0.0rc13
Requires-Dist: usd-exchange>=2.2.0
